pluto/__init__.py
pluto/data_engine.py
pluto/dataset.py
pluto/prompts.py
pluto/topic_tree.py
pluto/utils.py
pluto/posthog/__init__.py
pluto/posthog/events.py
pluto_data-0.5.0.dist-info/LICENSE
pluto_data-0.5.0.dist-info/METADATA
pluto_data-0.5.0.dist-info/WHEEL
pluto_data-0.5.0.dist-info/top_level.txt
pluto_data-0.5.0.dist-info/RECORD
