Metadata-Version: 2.1
Name: pluto-data
Version: 0.5.0
License-File: LICENSE
Requires-Dist: litellm (==1.7.12)
Requires-Dist: posthog (==2.5.0)
